CHANGES
MANIFEST.in
README
pytest_monkeyplus.py
setup.py
pytest_monkeyplus.egg-info/PKG-INFO
pytest_monkeyplus.egg-info/SOURCES.txt
pytest_monkeyplus.egg-info/dependency_links.txt
pytest_monkeyplus.egg-info/entry_points.txt
pytest_monkeyplus.egg-info/requires.txt
pytest_monkeyplus.egg-info/top_level.txt