Metadata-Version: 1.1
Name: pytest-monkeyplus
Version: 1.1.0
Summary: pytest's monkeypatch subclass with extra functionalities
Home-page: http://bitbucket.org/hsoft/pytest-monkeyplus/
Author: Virgil Dupras
Author-email: hsoft@hardcoded.net
License: UNKNOWN
Platform: UNKNOWN
Classifier: Development Status :: 5 - Production/Stable
Classifier: Intended Audience :: Developers
Classifier: License :: OSI Approved :: BSD License
Classifier: Programming Language :: Python :: 3
